Metadata-Version: 2.1
Name: aogram
Version: 1.2.46
Author: alexa
Author-email: example@gmail.com
Classifier: Programming Language :: Python :: 3.11
Classifier: License :: OSI Approved :: MIT License
Classifier: Operating System :: OS Independent
Requires-Python: >=3.7
Requires-Dist: magic-filter
Requires-Dist: aiohttp
Requires-Dist: pydantic
Requires-Dist: aiofiles
Requires-Dist: certifi
Requires-Dist: typing-extensions
